{
  "eventId": "mentoring-league-2025-02",
  "round": 1,
  "lastUpdated": "2025-02-16T21:08:47.844Z",
  "rankings": [
    {
      "playerId": 8,
      "rank": 1,
      "points": 3,
      "matches": 1,
      "wins": 1,
      "draws": 0,
      "losses": 0,
      "rating": 1020,
      "ratingChange": 20,
      "category": "ONYX",
      "playerDetails": {
        "name": "Géraldo",
        "currentRating": 1020,
        "category": "ONYX"
      }
    },
    {
      "playerId": 20,
      "rank": 1,
      "points": 3,
      "matches": 1,
      "wins": 1,
      "draws": 0,
      "losses": 0,
      "rating": 1020,
      "ratingChange": 20,
      "category": "ONYX",
      "playerDetails": {
        "name": "Pinocché",
        "currentRating": 1020,
        "category": "ONYX"
      }
    },
    {
      "playerId": 10,
      "rank": 1,
      "points": 3,
      "matches": 1,
      "wins": 1,
      "draws": 0,
      "losses": 0,
      "rating": 1020,
      "ratingChange": 20,
      "category": "ONYX",
      "playerDetails": {
        "name": "Joaïda",
        "currentRating": 1020,
        "category": "ONYX"
      }
    },
    {
      "playerId": 23,
      "rank": 1,
      "points": 3,
      "matches": 1,
      "wins": 1,
      "draws": 0,
      "losses": 0,
      "rating": 1020,
      "ratingChange": 20,
      "category": "ONYX",
      "playerDetails": {
        "name": "Référil",
        "currentRating": 1020,
        "category": "ONYX"
      }
    },
    {
      "playerId": 26,
      "rank": 1,
      "points": 3,
      "matches": 1,
      "wins": 1,
      "draws": 0,
      "losses": 0,
      "rating": 1020,
      "ratingChange": 20,
      "category": "ONYX",
      "playerDetails": {
        "name": "StWill",
        "currentRating": 1020,
        "category": "ONYX"
      }
    },
    {
      "playerId": 11,
      "rank": 1,
      "points": 3,
      "matches": 1,
      "wins": 1,
      "draws": 0,
      "losses": 0,
      "rating": 1020,
      "ratingChange": 20,
      "category": "ONYX",
      "playerDetails": {
        "name": "Joy",
        "currentRating": 1020,
        "category": "ONYX"
      }
    },
    {
      "playerId": 25,
      "rank": 1,
      "points": 3,
      "matches": 1,
      "wins": 1,
      "draws": 0,
      "losses": 0,
      "rating": 1020,
      "ratingChange": 20,
      "category": "ONYX",
      "playerDetails": {
        "name": "Solène",
        "currentRating": 1020,
        "category": "ONYX"
      }
    },
    {
      "playerId": 3,
      "rank": 8,
      "points": 1,
      "matches": 1,
      "wins": 1,
      "draws": 0,
      "losses": 0,
      "rating": 1020,
      "ratingChange": 20,
      "category": "ONYX",
      "playerDetails": {
        "name": "Divin",
        "currentRating": 1020,
        "category": "ONYX"
      }
    },
    {
      "playerId": 16,
      "rank": 8,
      "points": 1,
      "matches": 1,
      "wins": 1,
      "draws": 0,
      "losses": 0,
      "rating": 1020,
      "ratingChange": 20,
      "category": "ONYX",
      "playerDetails": {
        "name": "Mya",
        "currentRating": 1020,
        "category": "ONYX"
      }
    },
    {
      "playerId": 2,
      "rank": 8,
      "points": 1,
      "matches": 1,
      "wins": 1,
      "draws": 0,
      "losses": 0,
      "rating": 1020,
      "ratingChange": 20,
      "category": "ONYX",
      "playerDetails": {
        "name": "Charbel",
        "currentRating": 1020,
        "category": "ONYX"
      }
    },
    {
      "playerId": 4,
      "rank": 11,
      "points": 0,
      "matches": 1,
      "wins": 0,
      "draws": 0,
      "losses": 1,
      "rating": 980,
      "ratingChange": -20,
      "category": "ONYX",
      "playerDetails": {
        "name": "Elie",
        "currentRating": 980,
        "category": "ONYX"
      }
    },
    {
      "playerId": 18,
      "rank": 11,
      "points": 0,
      "matches": 1,
      "wins": 0,
      "draws": 0,
      "losses": 1,
      "rating": 980,
      "ratingChange": -20,
      "category": "ONYX",
      "playerDetails": {
        "name": "Oslie",
        "currentRating": 980,
        "category": "ONYX"
      }
    },
    {
      "playerId": 19,
      "rank": 11,
      "points": 0,
      "matches": 1,
      "wins": 0,
      "draws": 0,
      "losses": 1,
      "rating": 980,
      "ratingChange": -20,
      "category": "ONYX",
      "playerDetails": {
        "name": "Oswalde",
        "currentRating": 980,
        "category": "ONYX"
      }
    },
    {
      "playerId": 6,
      "rank": 11,
      "points": 0,
      "matches": 1,
      "wins": 0,
      "draws": 0,
      "losses": 1,
      "rating": 980,
      "ratingChange": -20,
      "category": "ONYX",
      "playerDetails": {
        "name": "Foréol",
        "currentRating": 980,
        "category": "ONYX"
      }
    },
    {
      "playerId": 24,
      "rank": 11,
      "points": 0,
      "matches": 1,
      "wins": 0,
      "draws": 0,
      "losses": 1,
      "rating": 980,
      "ratingChange": -20,
      "category": "ONYX",
      "playerDetails": {
        "name": "Rodrigue",
        "currentRating": 980,
        "category": "ONYX"
      }
    },
    {
      "playerId": 17,
      "rank": 11,
      "points": 0,
      "matches": 1,
      "wins": 0,
      "draws": 0,
      "losses": 1,
      "rating": 980,
      "ratingChange": -20,
      "category": "ONYX",
      "playerDetails": {
        "name": "Naofal",
        "currentRating": 980,
        "category": "ONYX"
      }
    },
    {
      "playerId": 22,
      "rank": 11,
      "points": 0,
      "matches": 1,
      "wins": 0,
      "draws": 0,
      "losses": 1,
      "rating": 980,
      "ratingChange": -20,
      "category": "ONYX",
      "playerDetails": {
        "name": "Raissa",
        "currentRating": 980,
        "category": "ONYX"
      }
    },
    {
      "playerId": 15,
      "rank": 11,
      "points": 0,
      "matches": 1,
      "wins": 0,
      "draws": 0,
      "losses": 1,
      "rating": 980,
      "ratingChange": -20,
      "category": "ONYX",
      "playerDetails": {
        "name": "Mickaël",
        "currentRating": 980,
        "category": "ONYX"
      }
    },
    {
      "playerId": 12,
      "rank": 11,
      "points": 0,
      "matches": 1,
      "wins": 0,
      "draws": 0,
      "losses": 1,
      "rating": 980,
      "ratingChange": -20,
      "category": "ONYX",
      "playerDetails": {
        "name": "Kevin",
        "currentRating": 980,
        "category": "ONYX"
      }
    },
    {
      "playerId": 5,
      "rank": 11,
      "points": 0,
      "matches": 1,
      "wins": 0,
      "draws": 0,
      "losses": 1,
      "rating": 980,
      "ratingChange": -20,
      "category": "ONYX",
      "playerDetails": {
        "name": "Elonm",
        "currentRating": 980,
        "category": "ONYX"
      }
    }
  ]
}